eslcli/__init__.py
eslcli/__main__.py
eslcli-0.12.1.dist-info/licenses/LICENSE
eslcli-0.12.1.dist-info/METADATA
eslcli-0.12.1.dist-info/WHEEL
eslcli-0.12.1.dist-info/top_level.txt
eslcli-0.12.1.dist-info/RECORD
